pypicloud_tools/__init__.py
pypicloud_tools/download.py
pypicloud_tools/lister.py
pypicloud_tools/rehost.py
pypicloud_tools/upload.py
pypicloud_tools/utils.py
pypicloud_tools-0.1.3.dist-info/DESCRIPTION.rst
pypicloud_tools-0.1.3.dist-info/METADATA
pypicloud_tools-0.1.3.dist-info/RECORD
pypicloud_tools-0.1.3.dist-info/WHEEL
pypicloud_tools-0.1.3.dist-info/entry_points.txt
pypicloud_tools-0.1.3.dist-info/metadata.json
pypicloud_tools-0.1.3.dist-info/top_level.txt
